{"version":1,"resource":"vscode-remote://wsl%2Bubuntu/home/ilya/app-redux/src/components/style.css","entries":[{"id":"9BZX.css","timestamp":1730287535211},{"id":"Q0Ij.css","timestamp":1730287582491},{"id":"e2UD.css","timestamp":1730287601031},{"id":"EPiP.css","timestamp":1730287689301},{"id":"iHZp.css","timestamp":1730287726831},{"id":"yOhB.css","timestamp":1730295639074},{"id":"Jnd0.css","timestamp":1730295654674},{"id":"wofW.css","timestamp":1730295679694},{"id":"GO6v.css","timestamp":1730400361935},{"id":"ddDB.css","timestamp":1730400400475},{"id":"tTiq.css","timestamp":1730400423145},{"id":"GHaf.css","timestamp":1730400447015},{"id":"gEWW.css","timestamp":1730400481535},{"id":"X5nK.css","timestamp":1730400506815},{"id":"68s9.css","timestamp":1730400675475},{"id":"EeLl.css","timestamp":1730400692075},{"id":"MP3j.css","timestamp":1730400702305},{"id":"b4DH.css","timestamp":1730400713185},{"id":"ZQ5F.css","timestamp":1730400765155},{"id":"u2Za.css","timestamp":1730400777895},{"id":"qVOi.css","timestamp":1730400857205},{"id":"G6Fj.css","timestamp":1730400867545},{"id":"zzQC.css","timestamp":1730401064115},{"id":"8nsx.css","timestamp":1730401084635},{"id":"2c8g.css","timestamp":1730401122955},{"id":"zz8O.css","timestamp":1730401143365},{"id":"bqc4.css","timestamp":1730401155155},{"id":"IMpO.css","timestamp":1730532124082},{"id":"J3Wf.css","timestamp":1730536230976},{"id":"QXGf.css","timestamp":1730536400766},{"id":"oSwO.css","timestamp":1730706774051},{"id":"vXFH.css","timestamp":1730796834918},{"id":"vYXC.css","timestamp":1730797078248},{"id":"etwJ.css","timestamp":1730797091078},{"id":"Bpdh.css","timestamp":1730797186408},{"id":"rNle.css","timestamp":1730879405545},{"id":"sdTd.css","timestamp":1730879454055},{"id":"uQh2.css","timestamp":1730879651565},{"id":"oqbO.css","timestamp":1730879672575},{"id":"3p9A.css","timestamp":1730879725525},{"id":"zPFa.css","timestamp":1730879737965},{"id":"uX1z.css","timestamp":1730879791075},{"id":"mVLD.css","timestamp":1730879823485},{"id":"mMsx.css","timestamp":1730879839615},{"id":"FIQZ.css","timestamp":1730879870955},{"id":"sTud.css","timestamp":1730880468385},{"id":"M1Pg.css","timestamp":1730880855095},{"id":"ZzmF.css","timestamp":1730906876970},{"id":"ekGH.css","timestamp":1730906887770},{"id":"edSK.css","timestamp":1730906911050}]}